moveread/dfy/__init__.py
moveread/dfy/__init__.pyi
moveread/dfy/_types.py
moveread/dfy/admin/__init__.py
moveread/dfy/admin/__init__.pyi
moveread/dfy/admin/admin.py
moveread/dfy/jobs/__init__.py
moveread/dfy/jobs/__init__.pyi
moveread/dfy/jobs/pairings.py
moveread/dfy/queries/__init__.py
moveread/dfy/queries/__init__.pyi
moveread/dfy/queries/api.py
moveread/dfy/queries/basic.py
moveread/dfy/queries/pairings.py
moveread/dfy/server/__init__.py
moveread/dfy/server/__init__.pyi
moveread/dfy/server/api.py
moveread/dfy/server/cli.py
moveread/dfy/server/clientgen_cli.py
moveread/dfy/server/main.py
moveread/dfy/server/pgns.py
moveread/dfy/server/sdk.py
moveread/dfy/server/util.py
moveread_dfy-0.1.38.dist-info/METADATA
moveread_dfy-0.1.38.dist-info/WHEEL
moveread_dfy-0.1.38.dist-info/entry_points.txt
moveread_dfy-0.1.38.dist-info/top_level.txt
moveread_dfy-0.1.38.dist-info/RECORD
