Metadata-Version: 2.1
Name: moveread-dfy
Version: 0.1.38
Summary: Moveread DFY data models and API
Author-email: Marcel Claramunt <marcel@moveread.com>
Project-URL: repo, https://github.com/moveread/moveread-dfy.git
Requires-Python: >=3.10
Requires-Dist: lazy-loader
Requires-Dist: pydantic
Requires-Dist: dslog
Requires-Dist: sqlmodel
Requires-Dist: sqltypes
Requires-Dist: python-kv[azure]
Requires-Dist: chess-scraping
Requires-Dist: chess-pairings
Requires-Dist: chess-utils
Provides-Extra: clientgen
Requires-Dist: openapi-ts ; extra == 'clientgen'
Provides-Extra: server
Requires-Dist: pure-cv ; extra == 'server'
Requires-Dist: fastapi ; extra == 'server'
Requires-Dist: python-multipart ; extra == 'server'
Requires-Dist: uvicorn[standard] ; extra == 'server'
Requires-Dist: python-kv[azure] ; extra == 'server'
Requires-Dist: psycopg2-binary ; extra == 'server'
Requires-Dist: dslog ; extra == 'server'
